django_red_admin_theme/__init__.py
django_red_admin_theme/static/.DS_Store
django_red_admin_theme/static/css/red_admin_theme.css
django_red_admin_theme/templates/.DS_Store
django_red_admin_theme/templates/admin/base_site.html
django_red_admin_theme-0.1.0.dist-info/licenses/LICENSE
django_red_admin_theme-0.1.0.dist-info/METADATA
django_red_admin_theme-0.1.0.dist-info/WHEEL
django_red_admin_theme-0.1.0.dist-info/top_level.txt
django_red_admin_theme-0.1.0.dist-info/RECORD
