Metadata-Version: 2.4
Name: django-red-admin-theme
Version: 0.1.0
Summary: A Django admin theme with a red color scheme
Author-email: Your Name <insiya.edu@gmail.com>
License: MIT License
Classifier: Framework :: Django
Classifier: Programming Language :: Python :: 3
Classifier: License :: OSI Approved :: MIT License
Requires-Python: >=3.8
License-File: LICENSE
Requires-Dist: Django>=3.2
Dynamic: license-file
